{
    "analyse_time": 1000,
    "awb_mode": "off",
    "brightfield_framerate": 891,
    "brightfield_resolution": 128,
    "exposure_mode": "off",
    "fluorescence_camera_pins": [
        8,
        10,
        12
    ],
    "fluorescence_exposure": 1000.0,
    "frame_buffer_length": 100,
    "frame_num": 0,
    "image_denoise": 0,
    "laser_trigger_pin": 22,
    "live": 1,
    "log": 0,
    "output_mode": "5V_BNC_Only",
    "period_dir": "period-data/",
    "predictionLatency": 15,
    "shutter_speed": 2500,
    "updateAfterNTriggers": 5,
    "usb_stages": {
        "current_position": 0,
        "encoding": "utf-8",
        "increment": 0.0005,
        "negative_limit": 0,
        "plane_address": 1,
        "positive_limit": 0.075,
        "terminators": [
            13,
            12
        ],
        "usb_XOnOff": 1,
        "usb_baudrate": 57600,
        "usb_dataBits": 8,
        "usb_name": "/dev/tty/USB0",
        "usb_parity": "Y",
        "usb_timeout": 0.1
    }
}